{
  "type_description_msg": {
    "type_description": {
      "type_name": "dexter_msgs/action/Fibonacci",
      "fields": [
        {
          "name": "goal",
          "type": {
            "type_id": 1,
            "capacity": 0,
            "string_capacity": 0,
            "nested_type_name": "dexter_msgs/action/Fibonacci_Goal"
          },
          "default_value": ""
        },
        {
          "name": "result",
          "type": {
            "type_id": 1,
            "capacity": 0,
            "string_capacity": 0,
            "nested_type_name": "dexter_msgs/action/Fibonacci_Result"
          },
          "default_value": ""
        },
        {
          "name": "feedback",
          "type": {
            "type_id": 1,
            "capacity": 0,
            "string_capacity": 0,
            "nested_type_name": "dexter_msgs/action/Fibonacci_Feedback"
          },
          "default_value": ""
        },
        {
          "name": "send_goal_service",
          "type": {
            "type_id": 1,
            "capacity": 0,
            "string_capacity": 0,
            "nested_type_name": "dexter_msgs/action/Fibonacci_SendGoal"
          },
          "default_value": ""
        },
        {
          "name": "get_result_service",
          "type": {
            "type_id": 1,
            "capacity": 0,
            "string_capacity": 0,
            "nested_type_name": "dexter_msgs/action/Fibonacci_GetResult"
          },
          "default_value": ""
        },
        {
          "name": "feedback_message",
          "type": {
            "type_id": 1,
            "capacity": 0,
            "string_capacity": 0,
            "nested_type_name": "dexter_msgs/action/Fibonacci_FeedbackMessage"
          },
          "default_value": ""
        }
      ]
    },
    "referenced_type_descriptions": [
      {
        "type_name": "builtin_interfaces/msg/Time",
        "fields": [
          {
            "name": "sec",
            "type": {
              "type_id": 6,
              "capacity": 0,
              "string_capacity": 0,
              "nested_type_name": ""
            },
            "default_value": ""
          },
          {
            "name": "nanosec",
            "type": {
              "type_id": 7,
              "capacity": 0,
              "string_capacity": 0,
              "nested_type_name": ""
            },
            "default_value": ""
          }
        ]
      },
      {
        "type_name": "dexter_msgs/action/Fibonacci_Feedback",
        "fields": [
          {
            "name": "partial_sequence",
            "type": {
              "type_id": 150,
              "capacity": 0,
              "string_capacity": 0,
              "nested_type_name": ""
            },
            "default_value": ""
          }
        ]
      },
      {
        "type_name": "dexter_msgs/action/Fibonacci_FeedbackMessage",
        "fields": [
          {
            "name": "goal_id",
            "type": {
              "type_id": 1,
              "capacity": 0,
              "string_capacity": 0,
              "nested_type_name": "unique_identifier_msgs/msg/UUID"
            },
            "default_value": ""
          },
          {
            "name": "feedback",
            "type": {
              "type_id": 1,
              "capacity": 0,
              "string_capacity": 0,
              "nested_type_name": "dexter_msgs/action/Fibonacci_Feedback"
            },
            "default_value": ""
          }
        ]
      },
      {
        "type_name": "dexter_msgs/action/Fibonacci_GetResult",
        "fields": [
          {
            "name": "request_message",
            "type": {
              "type_id": 1,
              "capacity": 0,
              "string_capacity": 0,
              "nested_type_name": "dexter_msgs/action/Fibonacci_GetResult_Request"
            },
            "default_value": ""
          },
          {
            "name": "response_message",
            "type": {
              "type_id": 1,
              "capacity": 0,
              "string_capacity": 0,
              "nested_type_name": "dexter_msgs/action/Fibonacci_GetResult_Response"
            },
            "default_value": ""
          },
          {
            "name": "event_message",
            "type": {
              "type_id": 1,
              "capacity": 0,
              "string_capacity": 0,
              "nested_type_name": "dexter_msgs/action/Fibonacci_GetResult_Event"
            },
            "default_value": ""
          }
        ]
      },
      {
        "type_name": "dexter_msgs/action/Fibonacci_GetResult_Event",
        "fields": [
          {
            "name": "info",
            "type": {
              "type_id": 1,
              "capacity": 0,
              "string_capacity": 0,
              "nested_type_name": "service_msgs/msg/ServiceEventInfo"
            },
            "default_value": ""
          },
          {
            "name": "request",
            "type": {
              "type_id": 97,
              "capacity": 1,
              "string_capacity": 0,
              "nested_type_name": "dexter_msgs/action/Fibonacci_GetResult_Request"
            },
            "default_value": ""
          },
          {
            "name": "response",
            "type": {
              "type_id": 97,
              "capacity": 1,
              "string_capacity": 0,
              "nested_type_name": "dexter_msgs/action/Fibonacci_GetResult_Response"
            },
            "default_value": ""
          }
        ]
      },
      {
        "type_name": "dexter_msgs/action/Fibonacci_GetResult_Request",
        "fields": [
          {
            "name": "goal_id",
            "type": {
              "type_id": 1,
              "capacity": 0,
              "string_capacity": 0,
              "nested_type_name": "unique_identifier_msgs/msg/UUID"
            },
            "default_value": ""
          }
        ]
      },
      {
        "type_name": "dexter_msgs/action/Fibonacci_GetResult_Response",
        "fields": [
          {
            "name": "status",
            "type": {
              "type_id": 2,
              "capacity": 0,
              "string_capacity": 0,
              "nested_type_name": ""
            },
            "default_value": ""
          },
          {
            "name": "result",
            "type": {
              "type_id": 1,
              "capacity": 0,
              "string_capacity": 0,
              "nested_type_name": "dexter_msgs/action/Fibonacci_Result"
            },
            "default_value": ""
          }
        ]
      },
      {
        "type_name": "dexter_msgs/action/Fibonacci_Goal",
        "fields": [
          {
            "name": "order",
            "type": {
              "type_id": 6,
              "capacity": 0,
              "string_capacity": 0,
              "nested_type_name": ""
            },
            "default_value": ""
          }
        ]
      },
      {
        "type_name": "dexter_msgs/action/Fibonacci_Result",
        "fields": [
          {
            "name": "sequence",
            "type": {
              "type_id": 150,
              "capacity": 0,
              "string_capacity": 0,
              "nested_type_name": ""
            },
            "default_value": ""
          }
        ]
      },
      {
        "type_name": "dexter_msgs/action/Fibonacci_SendGoal",
        "fields": [
          {
            "name": "request_message",
            "type": {
              "type_id": 1,
              "capacity": 0,
              "string_capacity": 0,
              "nested_type_name": "dexter_msgs/action/Fibonacci_SendGoal_Request"
            },
            "default_value": ""
          },
          {
            "name": "response_message",
            "type": {
              "type_id": 1,
              "capacity": 0,
              "string_capacity": 0,
              "nested_type_name": "dexter_msgs/action/Fibonacci_SendGoal_Response"
            },
            "default_value": ""
          },
          {
            "name": "event_message",
            "type": {
              "type_id": 1,
              "capacity": 0,
              "string_capacity": 0,
              "nested_type_name": "dexter_msgs/action/Fibonacci_SendGoal_Event"
            },
            "default_value": ""
          }
        ]
      },
      {
        "type_name": "dexter_msgs/action/Fibonacci_SendGoal_Event",
        "fields": [
          {
            "name": "info",
            "type": {
              "type_id": 1,
              "capacity": 0,
              "string_capacity": 0,
              "nested_type_name": "service_msgs/msg/ServiceEventInfo"
            },
            "default_value": ""
          },
          {
            "name": "request",
            "type": {
              "type_id": 97,
              "capacity": 1,
              "string_capacity": 0,
              "nested_type_name": "dexter_msgs/action/Fibonacci_SendGoal_Request"
            },
            "default_value": ""
          },
          {
            "name": "response",
            "type": {
              "type_id": 97,
              "capacity": 1,
              "string_capacity": 0,
              "nested_type_name": "dexter_msgs/action/Fibonacci_SendGoal_Response"
            },
            "default_value": ""
          }
        ]
      },
      {
        "type_name": "dexter_msgs/action/Fibonacci_SendGoal_Request",
        "fields": [
          {
            "name": "goal_id",
            "type": {
              "type_id": 1,
              "capacity": 0,
              "string_capacity": 0,
              "nested_type_name": "unique_identifier_msgs/msg/UUID"
            },
            "default_value": ""
          },
          {
            "name": "goal",
            "type": {
              "type_id": 1,
              "capacity": 0,
              "string_capacity": 0,
              "nested_type_name": "dexter_msgs/action/Fibonacci_Goal"
            },
            "default_value": ""
          }
        ]
      },
      {
        "type_name": "dexter_msgs/action/Fibonacci_SendGoal_Response",
        "fields": [
          {
            "name": "accepted",
            "type": {
              "type_id": 15,
              "capacity": 0,
              "string_capacity": 0,
              "nested_type_name": ""
            },
            "default_value": ""
          },
          {
            "name": "stamp",
            "type": {
              "type_id": 1,
              "capacity": 0,
              "string_capacity": 0,
              "nested_type_name": "builtin_interfaces/msg/Time"
            },
            "default_value": ""
          }
        ]
      },
      {
        "type_name": "service_msgs/msg/ServiceEventInfo",
        "fields": [
          {
            "name": "event_type",
            "type": {
              "type_id": 3,
              "capacity": 0,
              "string_capacity": 0,
              "nested_type_name": ""
            },
            "default_value": ""
          },
          {
            "name": "stamp",
            "type": {
              "type_id": 1,
              "capacity": 0,
              "string_capacity": 0,
              "nested_type_name": "builtin_interfaces/msg/Time"
            },
            "default_value": ""
          },
          {
            "name": "client_gid",
            "type": {
              "type_id": 51,
              "capacity": 16,
              "string_capacity": 0,
              "nested_type_name": ""
            },
            "default_value": ""
          },
          {
            "name": "sequence_number",
            "type": {
              "type_id": 8,
              "capacity": 0,
              "string_capacity": 0,
              "nested_type_name": ""
            },
            "default_value": ""
          }
        ]
      },
      {
        "type_name": "unique_identifier_msgs/msg/UUID",
        "fields": [
          {
            "name": "uuid",
            "type": {
              "type_id": 51,
              "capacity": 16,
              "string_capacity": 0,
              "nested_type_name": ""
            },
            "default_value": ""
          }
        ]
      }
    ]
  },
  "type_hashes": [
    {
      "type_name": "dexter_msgs/action/Fibonacci",
      "hash_string": "RIHS01_ef54392f230badd0c12acbcc081e356f503563d838f2e421b9728d3602cd8df2"
    },
    {
      "type_name": "builtin_interfaces/msg/Time",
      "hash_string": "RIHS01_b106235e25a4c5ed35098aa0a61a3ee9c9b18d197f398b0e4206cea9acf9c197"
    },
    {
      "type_name": "dexter_msgs/action/Fibonacci_Feedback",
      "hash_string": "RIHS01_9a84a73742ac12b1cfaee174eccb9ed88f8e7981d170c4341be824806369f8da"
    },
    {
      "type_name": "dexter_msgs/action/Fibonacci_FeedbackMessage",
      "hash_string": "RIHS01_eb15a68530c526b2724ee4b3c8956464d7125981e3d2e321cf537edbd30b66ff"
    },
    {
      "type_name": "dexter_msgs/action/Fibonacci_GetResult",
      "hash_string": "RIHS01_53a8153e6621abd9b2efbc6bab34b0b3026aa3e83c91f7ecb3a757a469bca9c7"
    },
    {
      "type_name": "dexter_msgs/action/Fibonacci_GetResult_Event",
      "hash_string": "RIHS01_05bb221a5fab68cdc61175419ab9886320f49ff24743f9cf272fe876316d4f4a"
    },
    {
      "type_name": "dexter_msgs/action/Fibonacci_GetResult_Request",
      "hash_string": "RIHS01_f32c7b162ca27a929247458c67fc2f3e29730002e7aff4db13060d419efd2c7e"
    },
    {
      "type_name": "dexter_msgs/action/Fibonacci_GetResult_Response",
      "hash_string": "RIHS01_989a9b34ccdb0856b9e01ee1ff9d29e97905139c8413b504086a12123aa07993"
    },
    {
      "type_name": "dexter_msgs/action/Fibonacci_Goal",
      "hash_string": "RIHS01_2a68131dfc8efdc4399ac98805da9ad7747d2ce8ee5082d04719f617e7500626"
    },
    {
      "type_name": "dexter_msgs/action/Fibonacci_Result",
      "hash_string": "RIHS01_a8f42901cdc3837cda44ce6120a52cbb47e85dbb84a41bdbfe5bd51b8f519bb8"
    },
    {
      "type_name": "dexter_msgs/action/Fibonacci_SendGoal",
      "hash_string": "RIHS01_d2a74de9c5120645d913d9c4a1b7fa7f9c81abe91aa9191832f28e5626165923"
    },
    {
      "type_name": "dexter_msgs/action/Fibonacci_SendGoal_Event",
      "hash_string": "RIHS01_52c560b9820805bf1b9325490da1c6888f3912ed55c392b9e34f693348543140"
    },
    {
      "type_name": "dexter_msgs/action/Fibonacci_SendGoal_Request",
      "hash_string": "RIHS01_023f87555f57676ab69763cc6effe285cab24a07b7ee47a03f618d7b6bcfd090"
    },
    {
      "type_name": "dexter_msgs/action/Fibonacci_SendGoal_Response",
      "hash_string": "RIHS01_54f8c0e96c65fdf7b74ac62ee0e6f6e4f9a549cdc5671b6857b1526ad47dc9a5"
    },
    {
      "type_name": "service_msgs/msg/ServiceEventInfo",
      "hash_string": "RIHS01_41bcbbe07a75c9b52bc96bfd5c24d7f0fc0a08c0cb7921b3373c5732345a6f45"
    },
    {
      "type_name": "unique_identifier_msgs/msg/UUID",
      "hash_string": "RIHS01_1b8e8aca958cbea28fe6ef60bf6c19b683c97a9ef60bb34752067d0f2f7ab437"
    }
  ]
}